[{"seen": ["122156"], "rate": ["8.7"], "imdb": [], "name": ["\u559c\u5bb4"]},
{"seen": ["252755"], "rate": ["8.3"], "imdb": ["http://www.imdb.com/title/tt1152282"], "name": ["\u7231\u5728\u66b9\u7f57 \u0e23\u0e31\u0e01\u0e41\u0e2b\u0e48\u0e07\u0e2a\u0e22\u0e32\u0e21"]},
{"seen": ["1033"], "rate": ["9.3"], "imdb": ["http://www.imdb.com/title/tt3464876"], "name": ["\u6781\u54c1\u57fa\u8001\u4f34 \u7b2c\u4e8c\u5b63 Vicious Season 2"]},
{"seen": ["231710"], "rate": ["8.4"], "imdb": [], "name": ["\u7a46\u8d6b\u5170\u9053 Mulholland Dr."]},
{"seen": ["187260"], "rate": ["8.6"], "imdb": [], "name": ["\u6a21\u4eff\u6e38\u620f The Imitation Game"]},
{"seen": ["315460"], "rate": ["8.3"], "imdb": ["http://www.imdb.com/title/tt0333764"], "name": ["\u84dd\u8272\u5927\u95e8 \u85cd\u8272\u5927\u9580"]},
{"seen": ["79804"], "rate": ["8.3"], "imdb": [], "name": ["\u963f\u9edb\u5c14\u7684\u751f\u6d3b La vie d'Ad\u00e8le"]},
{"seen": ["341809"], "rate": ["8.5"], "imdb": ["http://www.imdb.com/title/tt0388795"], "name": ["\u65ad\u80cc\u5c71 Brokeback Mountain"]},
{"seen": ["116655"], "rate": ["7.9"], "imdb": ["http://site.douban.com/movieclub/room/39071170/"], "name": ["\u70c8\u65e5\u707c\u5fc3"]},
{"seen": ["286"], "rate": ["9.0"], "imdb": [], "name": ["\u5361\u7f57\u5c14 Carol"]},
{"seen": ["2046"], "rate": ["8.7"], "imdb": [], "name": ["\u8d85\u611f\u730e\u6740 \u7b2c\u4e00\u5b63 Sense8 Season 1"]},
{"seen": ["242989"], "rate": ["8.7"], "imdb": [], "name": ["\u6625\u5149\u4e4d\u6cc4 \u6625\u5149\u4e4d\u6d29"]},
{"seen": ["598574"], "rate": ["9.4"], "imdb": [], "name": ["\u9738\u738b\u522b\u59ec"]},
{"seen": ["128830"], "rate": ["8.6"], "imdb": [], "name": ["\u8fbe\u62c9\u65af\u4e70\u5bb6\u4ff1\u4e50\u90e8 Dallas Buyers Club"]}][{"seen": ["231711"], "rate": ["8.4"], "imdb": [], "name": ["\u7a46\u8d6b\u5170\u9053 Mulholland Dr."]},
{"seen": ["187261"], "rate": ["8.6"], "imdb": [], "name": ["\u6a21\u4eff\u6e38\u620f The Imitation Game"]},
{"seen": ["1033"], "rate": ["9.3"], "imdb": ["http://www.imdb.com/title/tt3464876"], "name": ["\u6781\u54c1\u57fa\u8001\u4f34 \u7b2c\u4e8c\u5b63 Vicious Season 2"]},
{"seen": ["315461"], "rate": ["8.3"], "imdb": ["http://www.imdb.com/title/tt0333764"], "name": ["\u84dd\u8272\u5927\u95e8 \u85cd\u8272\u5927\u9580"]},
{"seen": ["13444"], "rate": ["7.8"], "imdb": [], "name": ["\u5047\u5c0f\u5b50 Tomboy"]},
{"seen": ["79804"], "rate": ["8.3"], "imdb": [], "name": ["\u963f\u9edb\u5c14\u7684\u751f\u6d3b La vie d'Ad\u00e8le"]},
{"seen": ["252755"], "rate": ["8.3"], "imdb": ["http://www.imdb.com/title/tt1152282"], "name": ["\u7231\u5728\u66b9\u7f57 \u0e23\u0e31\u0e01\u0e41\u0e2b\u0e48\u0e07\u0e2a\u0e22\u0e32\u0e21"]},
{"seen": ["122156"], "rate": ["8.7"], "imdb": [], "name": ["\u559c\u5bb4"]},
{"seen": ["341809"], "rate": ["8.5"], "imdb": ["http://www.imdb.com/title/tt0388795"], "name": ["\u65ad\u80cc\u5c71 Brokeback Mountain"]},
{"seen": ["3101"], "rate": ["7.5"], "imdb": [], "name": ["\u4eba\u95f4\u8272\u76f8"]},
{"seen": ["116664"], "rate": ["7.9"], "imdb": ["http://site.douban.com/movieclub/room/39071170/"], "name": ["\u70c8\u65e5\u707c\u5fc3"]},
{"seen": ["286"], "rate": ["9.0"], "imdb": [], "name": ["\u5361\u7f57\u5c14 Carol"]},
{"seen": ["2046"], "rate": ["8.7"], "imdb": [], "name": ["\u8d85\u611f\u730e\u6740 \u7b2c\u4e00\u5b63 Sense8 Season 1"]},
{"seen": ["242989"], "rate": ["8.7"], "imdb": [], "name": ["\u6625\u5149\u4e4d\u6cc4 \u6625\u5149\u4e4d\u6d29"]},
{"seen": ["128830"], "rate": ["8.6"], "imdb": [], "name": ["\u8fbe\u62c9\u65af\u4e70\u5bb6\u4ff1\u4e50\u90e8 Dallas Buyers Club"]},
{"seen": ["19213"], "rate": ["7.8"], "imdb": ["http://www.imdb.com/title/tt1532503"], "name": ["\u521d\u5b66\u8005 Beginners"]},
{"seen": ["17078"], "rate": ["7.7"], "imdb": [], "name": ["\u540c\u5fc3\u96be\u6539 I Can't Think Straight"]},
{"seen": ["17153"], "rate": ["7.5"], "imdb": [], "name": ["\u5047\u9762 \uac00\uba74"]},
{"seen": ["598576"], "rate": ["9.4"], "imdb": [], "name": ["\u9738\u738b\u522b\u59ec"]},
{"seen": ["4362"], "rate": ["7.4"], "imdb": [], "name": ["\u6c64\u59c6\u7684\u519c\u573a\u65c5\u884c Tom \u00e0 la Ferme"]},
{"seen": ["5079"], "rate": ["8.7"], "imdb": ["http://www.imdb.com/title/tt0248845"], "name": ["\u6447\u6eda\u82ad\u6bd4 Hedwig and the Angry Inch"]},
{"seen": ["70138"], "rate": ["6.8"], "imdb": [], "name": ["\u738b\u7684\u7537\u4eba \uc655\uc758\ub0a8\uc790"]},
{"seen": ["34960"], "rate": ["7.2"], "imdb": ["http://www.imdb.com/title/tt1616195"], "name": ["\u80e1\u4f5b J. Edgar"]},
{"seen": ["11"], "rate": [], "imdb": [], "name": ["\u8d85\u611f\u730e\u6740 \u7b2c\u4e8c\u5b63 Sense8 Season 2"]},
{"seen": ["17361"], "rate": ["7.9"], "imdb": ["http://www.imdb.com/title/tt0259744"], "name": ["\u591c\u5954"]},
{"seen": ["10844"], "rate": ["7.6"], "imdb": [], "name": ["\u5e7b\u60f3\u4e4b\u7231 Les amours imaginaires"]},
{"seen": ["2762"], "rate": ["7.0"], "imdb": [], "name": ["\u5723\u7f57\u5170\u4f20 Saint Laurent"]},
{"seen": ["3420"], "rate": ["7.6"], "imdb": ["http://www.imdb.com/title/tt0297884"], "name": ["\u8fdc\u79bb\u5929\u5802 Far from Heaven"]}][{"seen": ["1033"], "rate": ["9.3"], "imdb": ["http://www.imdb.com/title/tt3464876"], "name": ["\u6781\u54c1\u57fa\u8001\u4f34 \u7b2c\u4e8c\u5b63 Vicious Season 2"]},
{"seen": ["187263"], "rate": ["8.6"], "imdb": [], "name": ["\u6a21\u4eff\u6e38\u620f The Imitation Game"]},
{"seen": ["252755"], "rate": ["8.3"], "imdb": ["http://www.imdb.com/title/tt1152282"], "name": ["\u7231\u5728\u66b9\u7f57 \u0e23\u0e31\u0e01\u0e41\u0e2b\u0e48\u0e07\u0e2a\u0e22\u0e32\u0e21"]},
{"seen": ["315461"], "rate": ["8.3"], "imdb": ["http://www.imdb.com/title/tt0333764"], "name": ["\u84dd\u8272\u5927\u95e8 \u85cd\u8272\u5927\u9580"]},
{"seen": ["231711"], "rate": ["8.4"], "imdb": [], "name": ["\u7a46\u8d6b\u5170\u9053 Mulholland Dr."]},
{"seen": ["79804"], "rate": ["8.3"], "imdb": [], "name": ["\u963f\u9edb\u5c14\u7684\u751f\u6d3b La vie d'Ad\u00e8le"]},
{"seen": ["13444"], "rate": ["7.8"], "imdb": [], "name": ["\u5047\u5c0f\u5b50 Tomboy"]},
{"seen": ["122156"], "rate": ["8.7"], "imdb": [], "name": ["\u559c\u5bb4"]},
{"seen": ["341809"], "rate": ["8.5"], "imdb": ["http://www.imdb.com/title/tt0388795"], "name": ["\u65ad\u80cc\u5c71 Brokeback Mountain"]},
{"seen": ["242989"], "rate": ["8.7"], "imdb": [], "name": ["\u6625\u5149\u4e4d\u6cc4 \u6625\u5149\u4e4d\u6d29"]},
{"seen": ["116666"], "rate": ["7.9"], "imdb": ["http://site.douban.com/movieclub/room/39071170/"], "name": ["\u70c8\u65e5\u707c\u5fc3"]},
{"seen": ["2046"], "rate": ["8.7"], "imdb": [], "name": ["\u8d85\u611f\u730e\u6740 \u7b2c\u4e00\u5b63 Sense8 Season 1"]},
{"seen": ["128830"], "rate": ["8.6"], "imdb": [], "name": ["\u8fbe\u62c9\u65af\u4e70\u5bb6\u4ff1\u4e50\u90e8 Dallas Buyers Club"]},
{"seen": ["286"], "rate": ["9.0"], "imdb": [], "name": ["\u5361\u7f57\u5c14 Carol"]},
{"seen": ["598576"], "rate": ["9.4"], "imdb": [], "name": ["\u9738\u738b\u522b\u59ec"]},
{"seen": ["17078"], "rate": ["7.7"], "imdb": [], "name": ["\u540c\u5fc3\u96be\u6539 I Can't Think Straight"]},
{"seen": ["17153"], "rate": ["7.5"], "imdb": [], "name": ["\u5047\u9762 \uac00\uba74"]},
{"seen": ["70138"], "rate": ["6.8"], "imdb": [], "name": ["\u738b\u7684\u7537\u4eba \uc655\uc758\ub0a8\uc790"]},
{"seen": ["3101"], "rate": ["7.5"], "imdb": [], "name": ["\u4eba\u95f4\u8272\u76f8"]},
{"seen": ["5079"], "rate": ["8.7"], "imdb": ["http://www.imdb.com/title/tt0248845"], "name": ["\u6447\u6eda\u82ad\u6bd4 Hedwig and the Angry Inch"]},
{"seen": ["34960"], "rate": ["7.2"], "imdb": ["http://www.imdb.com/title/tt1616195"], "name": ["\u80e1\u4f5b J. Edgar"]},
{"seen": ["11"], "rate": [], "imdb": [], "name": ["\u8d85\u611f\u730e\u6740 \u7b2c\u4e8c\u5b63 Sense8 Season 2"]},
{"seen": ["4362"], "rate": ["7.4"], "imdb": [], "name": ["\u6c64\u59c6\u7684\u519c\u573a\u65c5\u884c Tom \u00e0 la Ferme"]},
{"seen": ["17361"], "rate": ["7.9"], "imdb": ["http://www.imdb.com/title/tt0259744"], "name": ["\u591c\u5954"]},
{"seen": ["19213"], "rate": ["7.8"], "imdb": ["http://www.imdb.com/title/tt1532503"], "name": ["\u521d\u5b66\u8005 Beginners"]},
{"seen": ["10844"], "rate": ["7.6"], "imdb": [], "name": ["\u5e7b\u60f3\u4e4b\u7231 Les amours imaginaires"]},
{"seen": ["2762"], "rate": ["7.0"], "imdb": [], "name": ["\u5723\u7f57\u5170\u4f20 Saint Laurent"]},
{"seen": ["3420"], "rate": ["7.6"], "imdb": ["http://www.imdb.com/title/tt0297884"], "name": ["\u8fdc\u79bb\u5929\u5802 Far from Heaven"]}][[[[[[[{"seen": ["17078"], "rate": ["7.7"], "imdb": [], "name": ["\u540c\u5fc3\u96be\u6539 I Can't Think Straight"]},
{"seen": ["4763"], "rate": ["8.3"], "imdb": [], "name": ["\u82f1\u56fd\u4eba\u5728\u7ebd\u7ea6 An Englishman in New York"]},
{"seen": ["27047"], "rate": ["8.9"], "imdb": [], "name": ["\u5929\u4f51\u9c8d\u6bd4 Prayers for Bobby"]},
{"seen": ["10082"], "rate": ["7.2"], "imdb": [], "name": ["\u5144\u5f1f\u60c5\u4eba Do Come\u00e7o ao Fim"]},
{"seen": ["15241"], "rate": ["8.1"], "imdb": [], "name": ["\u517b\u5b50\u5341\u4e94\u5c81 Patrik 1,5"]},
{"seen": ["341813"], "rate": ["8.5"], "imdb": ["http://www.imdb.com/title/tt0388795"], "name": ["\u65ad\u80cc\u5c71 Brokeback Mountain"]},
{"seen": ["6041"], "rate": ["8.4"], "imdb": [], "name": ["\u827e\u8349"]},
{"seen": ["60596"], "rate": ["8.4"], "imdb": [], "name": ["\u5355\u8eab\u7537\u5b50 A Single Man"]},
{"seen": ["6763"], "rate": ["8.4"], "imdb": [], "name": ["\u8ff7\u60c5\u7ad9\u53f0 Clapham Junction"]},
{"seen": ["8649"], "rate": ["7.9"], "imdb": [], "name": ["\u770b\u4e0d\u89c1\u7684\u4e16\u754c The World Unseen"]},
{"seen": ["12748"], "rate": ["8.1"], "imdb": ["http://www.imdb.com/title/tt0870089"], "name": ["\u4f60\u597d\uff0c\u518d\u89c1 Ciao"]},
{"seen": ["32035"], "rate": ["8.0"], "imdb": ["http://www.imdb.com/title/tt0942384"], "name": ["\u6b32\u76d6\u5f04\u6f6e Shelter"]},
{"seen": ["49328"], "rate": ["8.3"], "imdb": [], "name": ["\u7c73\u5c14\u514b Milk"]},
{"seen": ["1370"], "rate": ["8.6"], "imdb": [], "name": ["\u82f1\u4f26\u6027\u4e11\u95fb A Very British Sex Scandal"]},
{"seen": ["252755"], "rate": ["8.3"], "imdb": ["http://www.imdb.com/title/tt1152282"], "name": ["\u7231\u5728\u66b9\u7f57 \u0e23\u0e31\u0e01\u0e41\u0e2b\u0e48\u0e07\u0e2a\u0e22\u0e32\u0e21"]},
{"seen": ["12076"], "rate": ["7.2"], "imdb": ["http://www.imdb.com/title/tt0923779"], "name": ["\u7231\u6211\u751f\u6d3b Love My Life"]},
{"seen": ["23319"], "rate": ["8.3"], "imdb": [], "name": ["\u96cc\u96c4\u5927\u76d7 Bonnie and Clyde"]},
{"seen": ["5210"], "rate": ["8.0"], "imdb": [], "name": ["\u6211\u751f\u547d\u4e2d\u7684\u7537\u4eba L'homme de sa vie"]},
{"seen": ["16293"], "rate": ["8.0"], "imdb": ["http://www.imdb.com/title/tt0464049"], "name": ["\u5386\u53f2\u7cfb\u7537\u751f The History Boys"]},
{"seen": ["70138"], "rate": ["6.8"], "imdb": [], "name": ["\u738b\u7684\u7537\u4eba \uc655\uc758\ub0a8\uc790"]},
{"seen": ["134246"], "rate": ["7.2"], "imdb": [], "name": ["\u76db\u590f\u5149\u5e74"]},
{"seen": ["12302"], "rate": ["7.3"], "imdb": [], "name": ["\u4e0d\u540e\u6094 \ud6c4\ud68c\ud558\uc9c0 \uc54a\uc544"]},
{"seen": ["15474"], "rate": ["8.2"], "imdb": [], "name": ["\u7231\uff0c\u7b80\u5355 Hoje Eu Quero Voltar Sozinho"]},
{"seen": ["7904"], "rate": ["7.9"], "imdb": [], "name": ["\u591c\u95f4\u98de\u884c \uc57c\uac04\ube44\ud589"]},
{"seen": ["15902"], "rate": ["8.3"], "imdb": [], "name": ["\u9a84\u50b2 Pride"]},
{"seen": ["4343"], "rate": ["7.8"], "imdb": [], "name": ["\u7231\u5f88\u602a Love Is Strange"]},
{"seen": ["7037"], "rate": ["7.3"], "imdb": [], "name": ["\u6e56\u7554\u7684\u964c\u751f\u4eba L'Inconnu du lac"]},
{"seen": ["33655"], "rate": ["8.3"], "imdb": [], "name": ["\u5e73\u5e38\u7684\u5fc3 The Normal Heart"]},
{"seen": ["7347"], "rate": ["7.5"], "imdb": ["http://www.imdb.com/title/tt2617828"], "name": ["\u81ea\u7531\u5760\u843d Freier Fall"]},
{"seen": ["5098"], "rate": ["8.3"], "imdb": [], "name": ["\u590f\u5a01\u5937 Hawaii"]},
{"seen": ["79806"], "rate": ["8.3"], "imdb": [], "name": ["\u963f\u9edb\u5c14\u7684\u751f\u6d3b La vie d'Ad\u00e8le"]},
{"seen": ["4186"], "rate": ["6.8"], "imdb": [], "name": ["\u70b9\u4eae\u706f\u5149 Keep the Lights On"]},
{"seen": ["17327"], "rate": ["8.9"], "imdb": ["http://www.imdb.com/title/tt2357788"], "name": ["\u518d\u89c1\uff0c\u6211\u7684\u65b0\u90ce Bridegroom"]},
{"seen": ["6975"], "rate": ["7.2"], "imdb": [], "name": ["\u543b\u6211 Kyss mig"]},
{"seen": ["149692"], "rate": ["7.5"], "imdb": ["http://www.imdb.com/title/tt2319760"], "name": ["\u5973\u670b\u53cb\u25cb\u7537\u670b\u53cb"]},
{"seen": ["3517"], "rate": ["8.1"], "imdb": [], "name": ["\u7231\u82e5\u6b64\u65f6 Any Day Now"]},
{"seen": ["5240"], "rate": ["7.3"], "imdb": ["http://www.imdb.com/title/tt1625150"], "name": ["\u5fb7\u5dde\uff0c\u5317\u6d77 Noordzee, Texas"]},
{"seen": ["6944"], "rate": ["7.7"], "imdb": [], "name": ["\u4f1a\u66f4\u597d\u7684 \u0e44\u0e21\u0e48\u0e44\u0e14\u0e49\u0e02\u0e2d\u0e43\u0e2b\u0e49\u0e21\u0e32\u0e23\u0e31\u0e01"]},
{"seen": ["3147"], "rate": ["8.0"], "imdb": ["http://www.imdb.com/title/tt2318625"], "name": ["\u6697\u4e4b\u5149 \u05e2\u05dc\u05d8\u05d4"]},
{"seen": ["4217"], "rate": ["7.6"], "imdb": [], "name": ["\u8ff7\u5931\u5929\u5802 Hot boy N\u1ed5i Lo\u1ea1n- V\u00e0 C\u00e2u Chuy\u1ec7n V\u1ec1 Th\u1eb1ng C\u01b0\u1eddi, C\u00f4 G\u00e1i \u0110i\u1ebfm V\u00e0 Con V\u1ecbt"]},
{"seen": ["3870"], "rate": ["7.3"], "imdb": [], "name": ["\u514b\u91cc\u65af\u6258\u5f17\u53ca\u540c\u515a Christopher and His Kind"]},
{"seen": ["17045"], "rate": ["8.0"], "imdb": ["http://www.imdb.com/title/tt1714210"], "name": ["\u5468\u672b\u65f6\u5149 Weekend"]},
{"seen": ["6029"], "rate": ["8.2"], "imdb": ["http://www.imdb.com/title/tt0401085"], "name": ["\u7231\u75af\u72c2 C.R.A.Z.Y."]},
{"seen": ["61455"], "rate": ["7.9"], "imdb": [], "name": ["\u6211\u7231\u4f60\u83ab\u91cc\u65af I Love You Phillip Morris"]},
{"seen": ["12457"], "rate": ["8.1"], "imdb": ["http://www.imdb.com/title/tt0417189"], "name": ["\u65f6\u5149\u9a7b\u7559 Le temps qui reste"]},
{"seen": ["32609"], "rate": ["7.5"], "imdb": ["http://www.imdb.com/title/tt0842926"], "name": ["\u5b69\u5b50\u4eec\u90fd\u5f88\u597d The Kids Are All Right"]},
{"seen": ["60627"], "rate": ["7.1"], "imdb": [], "name": ["\u5f97\u95f2\u7092\u996d \u5f97\u9592\u7092\u98ef"]},
{"seen": ["110670"], "rate": ["7.6"], "imdb": ["http://www.imdb.com/title/tt1906518"], "name": ["\u60f3\u7231\u5c31\u7231 \u0e2d\u0e22\u0e32\u0e01\u0e23\u0e31\u0e01 \u0e01\u0e47\u0e23\u0e31\u0e01\u0e40\u0e25\u0e22"]},
{"seen": ["6177"], "rate": ["8.3"], "imdb": ["http://www.imdb.com/title/tt1368491"], "name": ["\u5fc3\u5e95\u7684\u9006\u6d41 Contracorriente"]},
{"seen": ["6444"], "rate": ["8.6"], "imdb": [], "name": ["\u9690\u85cf\u7684\u604b\u60c5 Un amour \u00e0 taire"]}]